{
    "key": "group_5d49e2413df04",
    "title": "Featured Image Thumbnail Adjustments",
    "fields": [
        {
            "key": "field_5d49e24d7f8ab",
            "label": "Select Alignment",
            "name": "thumbnail_select_alignment",
            "type": "select",
            "instructions": "",
            "required": 0,
            "conditional_logic": 0,
            "wrapper": {
                "width": "",
                "class": "",
                "id": ""
            },
            "choices": {
                "center": "Center",
                "left": "Left",
                "right": "Right"
            },
            "default_value": [],
            "allow_null": 0,
            "multiple": 0,
            "ui": 0,
            "return_format": "value",
            "ajax": 0,
            "placeholder": ""
        },
        {
            "key": "field_5d4c3ada8176a",
            "label": "Thumb Specific Image",
            "name": "thumb_specific_image",
            "type": "image",
            "instructions": "",
            "required": 0,
            "conditional_logic": 0,
            "wrapper": {
                "width": "",
                "class": "",
                "id": ""
            },
            "return_format": "array",
            "preview_size": "medium",
            "library": "all",
            "min_width": "",
            "min_height": "",
            "min_size": "",
            "max_width": "",
            "max_height": "",
            "max_size": "",
            "mime_types": ""
        },
        {
            "key": "field_5d5b034b87c53",
            "label": "Thumbnail Black and White",
            "name": "thumbnail_black_and_white",
            "type": "true_false",
            "instructions": "",
            "required": 0,
            "conditional_logic": 0,
            "wrapper": {
                "width": "",
                "class": "",
                "id": ""
            },
            "message": "",
            "default_value": 1,
            "ui": 0,
            "ui_on_text": "",
            "ui_off_text": ""
        }
    ],
    "location": [
        [
            {
                "param": "post_type",
                "operator": "==",
                "value": "post"
            }
        ]
    ],
    "menu_order": 0,
    "position": "side",
    "style": "default",
    "label_placement": "top",
    "instruction_placement": "label",
    "hide_on_screen": "",
    "active": 1,
    "description": "",
    "modified": 1566245724
}